[{"name":"acrylamide","pos":"noun","content":"<div class=\"entry\" sk=\"acrylamide: :0\" id=\"acrylamide\" hlength=\"10\" htag=\"section\" hclass=\"entry\" sum=\"272\" idm_id=\"000000463\"><div class=\"top-container\"><div class=\"top-g\" id=\"acrylamide_topg_1\"><div class=\"webtop\"><h1 class=\"headword\" htag=\"h1\" id=\"acrylamide_h_1\" hclass=\"headword\">acrylamide</h1> <span class=\"pos\" htag=\"span\" hclass=\"pos\">noun</span><span class=\"phonetics\"> <div class=\"phons_br\" htag=\"div\" geo=\"br\" wd=\"acrylamide\" hclass=\"phons_br\"><div class=\"sound audio_play_button pron-uk icon-audio\" data-src-mp3=\"https://www.oxfordlearnersdictionaries.com/media/english/uk_pron/a/acr/acryl/acrylamide__gb_1.mp3\" data-src-ogg=\"https://www.oxfordlearnersdictionaries.com/media/english/uk_pron_ogg/a/acr/acryl/acrylamide__gb_1.ogg\" title=\"acrylamide pronunciation\n                    English\" style=\"cursor: pointer\" valign=\"top\">&nbsp;</div><span class=\"phon\">/əˈkrɪləmaɪd/</span></div> <div class=\"phons_n_am\" geo=\"n_am\" htag=\"div\" hclass=\"phons_n_am\" wd=\"acrylamide\"><div class=\"sound audio_play_button pron-us icon-audio\" data-src-mp3=\"https://www.oxfordlearnersdictionaries.com/media/english/us_pron/a/acr/acryl/acrylamide__us_1.mp3\" data-src-ogg=\"https://www.oxfordlearnersdictionaries.com/media/english/us_pron_ogg/a/acr/acryl/acrylamide__us_1.ogg\" title=\"acrylamide pronunciation\n                    American\" style=\"cursor: pointer\" valign=\"top\">&nbsp;</div><span class=\"phon\">/əˈkrɪləmaɪd/</span></div></span><span class=\"grammar\" htag=\"span\" hclass=\"grammar\">[uncountable, countable]</span></div><a class=\"responsive_display_inline_on_smartphone link-right\" href=\"#relatedentries\">\n                            jump to other results\n                        </a></div></div><ol class=\"sense_single\" htag=\"ol\"><li class=\"sense\" htag=\"li\" id=\"acrylamide_sng_1\" hclass=\"sense\"><span class=\"sensetop\" hclass=\"sensetop\" htag=\"span\"><span class=\"def\" hclass=\"def\" htag=\"span\">a substance used in various industrial processes. <span class=\"dh\">Acrylamide</span> is also found in food that has been cooked at high temperatures, and may be a cause of cancer.</span></span><div class=\"collapse\" htag=\"div\" hclass=\"collapse\"><span class=\"unbox\" unbox=\"wordorigin\" id=\"acrylamide_unbox_1\"><span class=\"box_title\">Word Origin</span><span class=\"body\"><span class=\"p\">late 19th cent.: from <span class=\"eb\">acrylic</span> + <span class=\"ei\">amide</span>.</span></span></span></div>    \n</li></ol><span class=\"dictlink-g\"><span class=\"dictlink\">See <a class=\"Ref\" href=\"https://www.oxfordlearnersdictionaries.com/definition/american_english/acrylamide\" title=\" definition in American English\n \"><span class=\"xh\">acrylamide</span></a> in the Oxford Advanced American Dictionary</span></span><div class=\"pron-link\">Check pronunciation:\n                        <a href=\"https://www.oxfordlearnersdictionaries.com/pronunciation/english/acrylamide\">acrylamide</a></div></div>\n","matches":[],"relatives":[],"nearBys":["across adverb","acrostic noun","acrylamide noun","acrylic adjective","acrylic noun"]},[]]