[{"name":"prevalent","pos":"adjective","content":"<div class=\"entry\" sk=\"prevalent: :0\" htag=\"section\" id=\"prevalent\" hlength=\"9\" hclass=\"entry\" sum=\"495\" idm_id=\"000046639\"><div class=\"top-container\"><div class=\"top-g\" id=\"prevalent_topg_1\"><div class=\"webtop\"><h1 class=\"headword\" hclass=\"headword\" id=\"prevalent_h_1\" htag=\"h1\">prevalent</h1> <span class=\"pos\" htag=\"span\" hclass=\"pos\">adjective</span><span class=\"phonetics\"> <div class=\"phons_br\" htag=\"div\" geo=\"br\" hclass=\"phons_br\" wd=\"prevalent\"><div class=\"sound audio_play_button pron-uk icon-audio\" data-src-mp3=\"https://www.oxfordlearnersdictionaries.com/media/english/uk_pron/p/pre/preva/prevalent__gb_2.mp3\" data-src-ogg=\"https://www.oxfordlearnersdictionaries.com/media/english/uk_pron_ogg/p/pre/preva/prevalent__gb_2.ogg\" title=\"prevalent pronunciation\n                    English\" style=\"cursor: pointer\" valign=\"top\">&nbsp;</div><span class=\"phon\">/ˈprevələnt/</span></div> <div class=\"phons_n_am\" htag=\"div\" geo=\"n_am\" wd=\"prevalent\" hclass=\"phons_n_am\"><div class=\"sound audio_play_button pron-us icon-audio\" data-src-mp3=\"https://www.oxfordlearnersdictionaries.com/media/english/us_pron/p/pre/preva/prevalent__us_1.mp3\" data-src-ogg=\"https://www.oxfordlearnersdictionaries.com/media/english/us_pron_ogg/p/pre/preva/prevalent__us_1.ogg\" title=\"prevalent pronunciation\n                    American\" style=\"cursor: pointer\" valign=\"top\">&nbsp;</div><span class=\"phon\">/ˈprevələnt/</span></div></span><span class=\"labels\" hclass=\"labels\" htag=\"span\">(formal)</span></div><a class=\"responsive_display_inline_on_smartphone link-right\" href=\"#relatedentries\">\n                            jump to other results\n                        </a></div></div><ol class=\"sense_single\" htag=\"ol\"><li class=\"sense\" hclass=\"sense\" htag=\"li\" id=\"prevalent_sng_1\"><span class=\"sensetop\" hclass=\"sensetop\" htag=\"span\"><span class=\"def\" htag=\"span\" hclass=\"def\">that exists or is very common at a particular time or in a particular place</span></span> <span class=\"xrefs\" xt=\"nsyn\" hclass=\"xrefs\" htag=\"span\"><span class=\"prefix\">synonym</span> <a class=\"Ref\" href=\"https://www.oxfordlearnersdictionaries.com/definition/english/common_1\" title=\"common definition\"><span class=\"xr-g\" href=\"common_subentryg_1:common_topg_2\" bord=\"n\"><span class=\"xh\">common</span></span></a><span class=\"sep\">,</span> <a class=\"Ref\" href=\"https://www.oxfordlearnersdictionaries.com/definition/english/widespread\" title=\"widespread definition\"><span class=\"xr-g\" href=\"widespread_e\" bord=\"n\"><span class=\"xh\">widespread</span></span></a></span><ul class=\"examples\" hclass=\"examples\" htag=\"ul\"><li class=\"\" htag=\"li\"><span class=\"x\">a prevalent view</span></li><li class=\"\" htag=\"li\"> <span class=\"cf\" htag=\"span\" hclass=\"cf\">prevalent among somebody</span> <span class=\"x\">These prejudices are particularly prevalent among people living in the North.</span></li><li class=\"\" htag=\"li\"> <span class=\"cf\" htag=\"span\" hclass=\"cf\">prevalent in somebody/something</span> <span class=\"x\">The disease is even more prevalent in Latin America.</span></li></ul><div class=\"collapse\" htag=\"div\" hclass=\"collapse\"><span class=\"unbox\" unbox=\"extra_examples\" id=\"prevalent_unbox_1\"><span class=\"box_title\">Extra Examples</span><ul class=\"examples\" hclass=\"examples\" htag=\"ul\"><li class=\"\" htag=\"li\"><span class=\"unx\">This attitude is prevalent among teenagers.</span></li><li class=\"\" htag=\"li\"><span class=\"unx\">Our diet contributes to the high levels of heart disease prevalent in this country.</span></li><li class=\"\" htag=\"li\"><span class=\"unx\">Temporary working is most prevalent among people in service occupations.</span></li><li class=\"\" htag=\"li\"><span class=\"unx\">Truancy is most prevalent near the end of compulsory schooling.</span></li></ul></span></div><div class=\"collapse\" htag=\"div\" hclass=\"collapse\"><span class=\"unbox\" unbox=\"wordorigin\" id=\"prevalent_unbox_2\"><span class=\"box_title\">Word Origin</span><span class=\"body\"><span class=\"p\">late 16th cent.: from Latin <span class=\"ei\">praevalent-</span> ‘having greater power’, from the verb <span class=\"ei\">praevalere</span> ‘have greater power’, from <span class=\"ei\">prae</span> ‘before’ + <span class=\"ei\">valere</span> ‘have power’.</span></span></span></div>    \n</li></ol><span class=\"dictlink-g\"><span class=\"dictlink\">See <a class=\"Ref\" href=\"https://www.oxfordlearnersdictionaries.com/definition/american_english/prevalent\" title=\" definition in American English\n \"><span class=\"xh\">prevalent</span></a> in the Oxford Advanced American Dictionary</span><span class=\"dictlink\">See <a class=\"Ref\" href=\"https://www.oxfordlearnersdictionaries.com/definition/academic/prevalent\" title=\" definition in Academic English\n \"><span class=\"xh\">prevalent</span></a> in the Oxford Learner's Dictionary of Academic English</span></span><div class=\"pron-link\">Check pronunciation:\n                        <a href=\"https://www.oxfordlearnersdictionaries.com/pronunciation/english/prevalent\">prevalent</a></div></div>\n","matches":[],"relatives":[],"nearBys":["prevail upon to do phrasal verb","prevalence noun","prevalent adjective","prevaricate verb","prevarication noun"]},[]]