[{"name":"readership","pos":"noun","content":"<div class=\"entry\" hclass=\"entry\" sum=\"728\" sk=\"readership: :0\" htag=\"section\" id=\"readership\" hlength=\"10\" idm_id=\"000048752\"><div class=\"top-container\"><div class=\"top-g\" id=\"readership_topg_1\"><div class=\"webtop\"><h1 class=\"headword\" hclass=\"headword\" htag=\"h1\" id=\"readership_h_1\">readership</h1> <span class=\"pos\" htag=\"span\" hclass=\"pos\">noun</span><span class=\"phonetics\"> <div class=\"phons_br\" hclass=\"phons_br\" wd=\"readership\" geo=\"br\" htag=\"div\"><div class=\"sound audio_play_button pron-uk icon-audio\" data-src-mp3=\"https://www.oxfordlearnersdictionaries.com/media/english/uk_pron/r/rea/reade/readership__gb_1.mp3\" data-src-ogg=\"https://www.oxfordlearnersdictionaries.com/media/english/uk_pron_ogg/r/rea/reade/readership__gb_1.ogg\" title=\"readership pronunciation\n                    English\" style=\"cursor: pointer\" valign=\"top\">&nbsp;</div><span class=\"phon\">/ˈriːdəʃɪp/</span></div> <div class=\"phons_n_am\" geo=\"n_am\" htag=\"div\" wd=\"readership\" hclass=\"phons_n_am\"><div class=\"sound audio_play_button pron-us icon-audio\" data-src-mp3=\"https://www.oxfordlearnersdictionaries.com/media/english/us_pron/r/rea/reade/readership__us_1.mp3\" data-src-ogg=\"https://www.oxfordlearnersdictionaries.com/media/english/us_pron_ogg/r/rea/reade/readership__us_1.ogg\" title=\"readership pronunciation\n                    American\" style=\"cursor: pointer\" valign=\"top\">&nbsp;</div><span class=\"phon\">/ˈriːdərʃɪp/</span></div></span> </div><a class=\"responsive_display_inline_on_smartphone link-right\" href=\"#relatedentries\">\n                            jump to other results\n                        </a></div></div><ol class=\"senses_multiple\" htag=\"ol\"><li class=\"sense\" sensenum=\"1\" hclass=\"sense\" id=\"readership_sng_1\" cefr=\"c1\" htag=\"li\"><a class=\"open oup_icons\" title=\"Add to My Word Lists\"><span class=\"star-btn\" aria-hidden=\"true\">​</span></a><span class=\"sensetop\" htag=\"span\" hclass=\"sensetop\"><span class=\"grammar\" htag=\"span\" hclass=\"grammar\">[usually singular]</span></span> <span class=\"def\" htag=\"span\" hclass=\"def\">the number or type of people who read a particular newspaper, magazine, etc.</span><ul class=\"examples\" hclass=\"examples\" htag=\"ul\"><li class=\"\" htag=\"li\"><span class=\"x\">a readership of around 10 000</span></li><li class=\"\" htag=\"li\"><span class=\"x\">In its new format, the magazine hopes to attract a much wider readership.</span></li><li class=\"\" htag=\"li\"><span class=\"x\">a female readership</span></li><li class=\"\" htag=\"li\"><span class=\"x\">As an author she has a small but loyal readership.</span></li></ul><span class=\"topic-g\"><span class=\"prefix\">Topics </span><a class=\"Ref\" href=\"https://www.oxfordlearnersdictionaries.com/topic/tv-radio-and-news?level=c1\" title=\"Topic tv-radio-and-news\"><span class=\"topic\" href=\"l2:culture:tv_radio_and_news?cefr=c1\"><span class=\"topic_name\">TV, radio and news</span><span class=\"topic_cefr\">c1</span></span></a></span>          \n</li><li class=\"sense\" htag=\"li\" id=\"readership_sng_2\" cefr=\"c2\" corpus_src=\"unknown\" bord=\"y\" hclass=\"sense\" corpus_freq=\"10\" sensenum=\"2\"><a class=\"open oup_icons\" title=\"Add to My Word Lists\"><span class=\"star-btn\" aria-hidden=\"true\">​</span></a><span class=\"sensetop\" hclass=\"sensetop\" htag=\"span\"><div class=\"variants\" hclass=\"variants\" type=\"vs\" htag=\"div\">(usually <span class=\"v-g\"><span class=\"v\" q=\"usu\">Readership</span></span>)</div></span> <span class=\"cf\" hclass=\"cf\" htag=\"span\">readership (in something)</span> <span class=\"labels\" hclass=\"labels\" htag=\"span\">(British English)</span> <span class=\"def\" htag=\"span\" hclass=\"def\">the position of a <a class=\"Ref\" href=\"https://www.oxfordlearnersdictionaries.com/definition/english/reader#reader_sng_4\" title=\"Reader definition\"><span class=\"ndv\">Reader</span></a> at a university</span><ul class=\"examples\" htag=\"ul\" hclass=\"examples\"><li class=\"\" htag=\"li\"><span class=\"x\">She currently holds a Readership in Geography at the University of Hull.</span></li></ul><span class=\"topic-g\"><span class=\"prefix\">Topics </span><a class=\"Ref\" href=\"https://www.oxfordlearnersdictionaries.com/topic/education?level=c2\" title=\"Topic education\"><span class=\"topic\" href=\"l2:people:education?cefr=c2\"><span class=\"topic_name\">Education</span><span class=\"topic_cefr\">c2</span></span></a></span>      </li></ol><span class=\"dictlink-g\"><span class=\"dictlink\">See <a class=\"Ref\" href=\"https://www.oxfordlearnersdictionaries.com/definition/american_english/readership\" title=\" definition in American English\n \"><span class=\"xh\">readership</span></a> in the Oxford Advanced American Dictionary</span><span class=\"dictlink\">See <a class=\"Ref\" href=\"https://www.oxfordlearnersdictionaries.com/definition/academic/readership\" title=\" definition in Academic English\n \"><span class=\"xh\">readership</span></a> in the Oxford Learner's Dictionary of Academic English</span></span><div class=\"pron-link\">Check pronunciation:\n                        <a href=\"https://www.oxfordlearnersdictionaries.com/pronunciation/english/readership\">readership</a></div></div>\n","matches":[],"relatives":[],"nearBys":["reader noun","Reader's Digest","readership noun","readily adverb","read-in noun"]},[]]