[{"name":"thirty","pos":"number","content":"<div class=\"entry\" hclass=\"entry\" sum=\"287\" sk=\"thirty: :0\" htag=\"section\" id=\"thirty\" hlength=\"6\" idm_id=\"000060965\"><div class=\"top-container\"><div class=\"top-g\" id=\"thirty_topg_1\"><div class=\"webtop\"><h1 class=\"headword\" random=\"y\" hclass=\"headword\" htag=\"h1\" id=\"thirty_h_1\" ox3000=\"y\">thirty</h1> <div class=\"symbols\" hclass=\"symbols\" htag=\"div\"><a href=\"https://www.oxfordlearnersdictionaries.com/wordlists/oxford3000-5000?dataset=english&amp;list=ox3000&amp;level=a1\"><span class=\"ox3ksym_a1\">&nbsp;</span></a></div><span class=\"phonetics\"> <div class=\"phons_br\" htag=\"div\" geo=\"br\" hclass=\"phons_br\" wd=\"thirty\"><div class=\"sound audio_play_button pron-uk icon-audio\" data-src-mp3=\"https://www.oxfordlearnersdictionaries.com/media/english/uk_pron/t/thi/thirt/thirty__gb_2.mp3\" data-src-ogg=\"https://www.oxfordlearnersdictionaries.com/media/english/uk_pron_ogg/t/thi/thirt/thirty__gb_2.ogg\" title=\"thirty pronunciation\n                    English\" style=\"cursor: pointer\" valign=\"top\">&nbsp;</div><span class=\"phon\">/ˈθɜːti/</span></div> <div class=\"phons_n_am\" hclass=\"phons_n_am\" wd=\"thirty\" geo=\"n_am\" htag=\"div\"><div class=\"sound audio_play_button pron-us icon-audio\" data-src-mp3=\"https://www.oxfordlearnersdictionaries.com/media/english/us_pron/t/thi/thirt/thirty__us_1.mp3\" data-src-ogg=\"https://www.oxfordlearnersdictionaries.com/media/english/us_pron_ogg/t/thi/thirt/thirty__us_1.ogg\" title=\"thirty pronunciation\n                    American\" style=\"cursor: pointer\" valign=\"top\">&nbsp;</div><span class=\"phon\">/ˈθɜːrti/</span></div></span><span class=\"jumplinks\"><a class=\"Ref\" href=\"https://www.oxfordlearnersdictionaries.com/definition/english/thirty#thirty_idmgs_1\" title=\"Idioms definition\"><span class=\"jumplink\" name=\"Idioms\" href=\"thirty_idmgs_1\">Idioms</span></a> </span></div><a class=\"responsive_display_inline_on_smartphone link-right\" href=\"#relatedentries\">\n                            jump to other results\n                        </a></div></div><ol class=\"senses_multiple\" htag=\"ol\"><li class=\"sense\" ox3000=\"y\" id=\"thirty_sng_1\" cefr=\"a1\" htag=\"li\" sensenum=\"1\" hclass=\"sense\"><span class=\"sensetop\" hclass=\"sensetop\" htag=\"span\"><div class=\"symbols\" hclass=\"symbols\" htag=\"div\"><a href=\"https://www.oxfordlearnersdictionaries.com/wordlists/oxford3000-5000?dataset=english&amp;list=ox3000&amp;level=a1\"><span class=\"ox3ksym_a1\">&nbsp;</span></a></div></span> <span class=\"pos\" hclass=\"pos\" htag=\"span\">number</span> <span class=\"def\" hclass=\"def\" htag=\"span\">30</span>          \n</li><li class=\"sense\" hclass=\"sense\" sensenum=\"2\" htag=\"li\" id=\"thirty_sng_2\"><span class=\"sensetop\" htag=\"span\" hclass=\"sensetop\"><span class=\"pos\" hclass=\"pos\" htag=\"span\">noun</span></span> <div class=\"variants\" htag=\"div\" type=\"alt\" hclass=\"variants\"><span class=\"v-g\"><span class=\"v\">the thirties</span></span></div> <span class=\"grammar\" htag=\"span\" hclass=\"grammar\">[plural]</span> <span class=\"def\" htag=\"span\" hclass=\"def\">numbers, years or temperatures from 30 to 39</span>                                     <div class=\"parallax-container \" data-iaw=\"container\">\n        <div class=\"parallax-abs\">\n            <div id=\"ad_contentslot_1\" class=\"am-default contentslot parallax-fix\">\n                <script>iaw.cmd.push(function() { iaw.display('ad_contentslot_1'); });</script>\n            </div>\n        </div>\n    </div>\n             </li></ol><div class=\"idioms\" htag=\"div\" id=\"thirty_idmgs_1\" hclass=\"idioms\"><span class=\"idioms_heading\">Idioms</span> <span class=\"idm-g\" id=\"thirty_idmg_1\" sk=\"inthirties\"><div class=\"top-container\"><div class=\"top-g\" id=\"thirty_topg_2\"><div class=\"webtop\"><span class=\"idm\" id=\"thirty_idm_1\">in your thirties</span> </div></div></div><ol class=\"sense_single\" htag=\"ol\"><li class=\"sense\" id=\"thirty_sng_3\" htag=\"li\" hclass=\"sense\"><span class=\"sensetop\" htag=\"span\" hclass=\"sensetop\"><span class=\"def\" hclass=\"def\" htag=\"span\">between the ages of 30 and 39</span></span>      </li></ol></span></div><span class=\"dictlink-g\"><span class=\"dictlink\">See <a class=\"Ref\" href=\"https://www.oxfordlearnersdictionaries.com/definition/american_english/thirty\" title=\" definition in American English\n \"><span class=\"xh\">thirty</span></a> in the Oxford Advanced American Dictionary</span></span><div class=\"pron-link\">Check pronunciation:\n                        <a href=\"https://www.oxfordlearnersdictionaries.com/pronunciation/english/thirty\">thirty</a></div></div>\n","matches":["thirty-second note noun","the thirty-year rule noun","Thirty days hath September","the Thirty-nine Articles","thirty-second note","thirty-year rule","thirty-second notes"],"relatives":["thirty-second note noun","the thirty-year rule noun","Thirty days hath September","the Thirty-nine Articles","thirty-second note","thirty-year rule","thirty-second notes"],"nearBys":["thirtieth noun","thirtieth ordinal number","thirty","Thirty days hath September","the 38th parallel"]},[{"name":"thirty-second note","pos":"noun","content":"<div class=\"entry\" htag=\"section\" id=\"thirty-second-note\" hlength=\"18\" sk=\"thirtysecondnote: :15\" sum=\"291\" hclass=\"entry\" idm_id=\"000060970\"><div class=\"top-container\"><div class=\"top-g\" id=\"thirty_second_note_topg_1\"><div class=\"webtop\"><h1 class=\"headword\" htag=\"h1\" id=\"thirty_second_note_h_1\" hclass=\"headword\">thirty-second note</h1> <span class=\"pos\" htag=\"span\" hclass=\"pos\">noun</span><span class=\"phonetics\"> <div class=\"phons_br\" htag=\"div\" geo=\"br\" wd=\"thirty-second note\" hclass=\"phons_br\"><div class=\"sound audio_play_button pron-uk icon-audio\" data-src-mp3=\"https://www.oxfordlearnersdictionaries.com/media/english/uk_pron/t/thi/thirt/thirty_second_note_1_gb_1.mp3\" data-src-ogg=\"https://www.oxfordlearnersdictionaries.com/media/english/uk_pron_ogg/t/thi/thirt/thirty_second_note_1_gb_1.ogg\" title=\"thirty-second note pronunciation\n                    English\" style=\"cursor: pointer\" valign=\"top\">&nbsp;</div><span class=\"phon\">/ˌθɜːti ˈsekənd nəʊt/</span></div> <div class=\"phons_n_am\" htag=\"div\" geo=\"n_am\" wd=\"thirty-second note\" hclass=\"phons_n_am\"><div class=\"sound audio_play_button pron-us icon-audio\" data-src-mp3=\"https://www.oxfordlearnersdictionaries.com/media/english/us_pron/t/thi/thirt/thirty_second_note_1_us_1.mp3\" data-src-ogg=\"https://www.oxfordlearnersdictionaries.com/media/english/us_pron_ogg/t/thi/thirt/thirty_second_note_1_us_1.ogg\" title=\"thirty-second note pronunciation\n                    American\" style=\"cursor: pointer\" valign=\"top\">&nbsp;</div><span class=\"phon\">/ˌθɜːrti ˈsekənd nəʊt/</span></div></span><span class=\"labels\" htag=\"span\" hclass=\"labels\">(North American English)</span> <div class=\"variants\" id=\"thirty_second_note_vgs_1\" htag=\"div\" type=\"vf\" hclass=\"variants\">(<span class=\"v-g\" id=\"thirty_second_note_vg_1\"><span class=\"labels\" hclass=\"labels\" htag=\"span\">British English</span> <span class=\"v\" id=\"thirty_second_note_v_1\">demisemiquaver</span></span>)</div> <span class=\"labels\" hclass=\"labels\" htag=\"span\">(<span class=\"subj\" subj=\"music\" id=\"thirty_second_note_subj_1\">music</span>)</span></div><a class=\"responsive_display_inline_on_smartphone link-right\" href=\"#relatedentries\">\n                            jump to other results\n                        </a></div></div><ol class=\"sense_single\" htag=\"ol\"><li class=\"sense\" hclass=\"sense\" id=\"thirtysecondnote_sng_1\" htag=\"li\"><span class=\"sensetop\" hclass=\"sensetop\" htag=\"span\"><span class=\"def\" htag=\"span\" hclass=\"def\">a note that lasts as long as half a <a class=\"Ref\" href=\"https://www.oxfordlearnersdictionaries.com/definition/english/semiquaver\" title=\"semiquaver definition\"><span class=\"ndv\">semiquaver</span></a></span></span>    \n</li></ol><span class=\"dictlink-g\"><span class=\"dictlink\">See <a class=\"Ref\" href=\"https://www.oxfordlearnersdictionaries.com/definition/american_english/thirty-second-note\" title=\" definition in American English\n \"><span class=\"xh\">thirty-second note</span></a> in the Oxford Advanced American Dictionary</span></span><div class=\"pron-link\">Check pronunciation:\n                        <a href=\"https://www.oxfordlearnersdictionaries.com/pronunciation/english/thirty-second-note\">thirty-second note</a></div></div>\n","matches":["thirty-second note"],"relatives":["thirty-second note"],"nearBys":["35 mm noun","the Thirty-nine Articles","thirty-second note noun","the thirty-year rule noun","this determiner, pronoun"]},{"name":"the thirty-year rule","pos":"noun","content":"<div class=\"entry\" htag=\"section\" id=\"the-thirty-year-rule\" hlength=\"20\" sk=\"thirtyyearrule: :20\" sum=\"348\" hclass=\"entry\" idm_id=\"000060971\"><div class=\"top-container\"><div class=\"top-g\" id=\"the_thirty_year_rule_topg_1\"><div class=\"webtop\"><h1 class=\"headword\" htag=\"h1\" id=\"the_thirty_year_rule_h_1\" hclass=\"headword\"><span class=\"st\" id=\"the_thirty_year_rule_st_1\">the</span> thirty-year rule</h1> <span class=\"pos\" htag=\"span\" hclass=\"pos\">noun</span><span class=\"phonetics\"> <div class=\"phons_br\" wd=\"the thirty-year rule\" hclass=\"phons_br\" geo=\"br\" htag=\"div\"><div class=\"sound audio_play_button pron-uk icon-audio\" data-src-mp3=\"https://www.oxfordlearnersdictionaries.com/media/english/uk_pron/t/thi/thirt/thirty_year_rule_1_gb_1.mp3\" data-src-ogg=\"https://www.oxfordlearnersdictionaries.com/media/english/uk_pron_ogg/t/thi/thirt/thirty_year_rule_1_gb_1.ogg\" title=\"the thirty-year rule pronunciation\n                    English\" style=\"cursor: pointer\" valign=\"top\">&nbsp;</div><span class=\"phon\">/ðə ˌθɜːti ˈjɪə ruːl/</span><span class=\"sep\">,</span> <div class=\"sound audio_play_button pron-uk icon-audio\" data-src-mp3=\"https://www.oxfordlearnersdictionaries.com/media/english/uk_pron/t/the/the_t/the_thirty_year_rule_1_gb_1.mp3\" data-src-ogg=\"https://www.oxfordlearnersdictionaries.com/media/english/uk_pron_ogg/t/the/the_t/the_thirty_year_rule_1_gb_1.ogg\" title=\"the thirty-year rule pronunciation\n                    English\" style=\"cursor: pointer\" valign=\"top\">&nbsp;</div><span class=\"phon\">/ðə ˌθɜːti ˈjɜː ruːl/</span></div> <div class=\"phons_n_am\" geo=\"n_am\" htag=\"div\" wd=\"the thirty-year rule\" hclass=\"phons_n_am\"><div class=\"sound audio_play_button pron-us icon-audio\" data-src-mp3=\"https://www.oxfordlearnersdictionaries.com/media/english/us_pron/t/thi/thirt/thirty_year_rule_1_us_1.mp3\" data-src-ogg=\"https://www.oxfordlearnersdictionaries.com/media/english/us_pron_ogg/t/thi/thirt/thirty_year_rule_1_us_1.ogg\" title=\"the thirty-year rule pronunciation\n                    American\" style=\"cursor: pointer\" valign=\"top\">&nbsp;</div><span class=\"phon\">/ðə ˌθɜːrti ˈjɪr ruːl/</span></div></span><span class=\"grammar\" htag=\"span\" hclass=\"grammar\">[singular]</span></div><a class=\"responsive_display_inline_on_smartphone link-right\" href=\"#relatedentries\">\n                            jump to other results\n                        </a></div></div><ol class=\"sense_single\" htag=\"ol\"><li class=\"sense\" htag=\"li\" id=\"thirtyyearrule_sng_1\" hclass=\"sense\"><span class=\"sensetop\" htag=\"span\" hclass=\"sensetop\"><span class=\"def\" htag=\"span\" hclass=\"def\">a British government rule which prevented certain official documents from being made public until a period of thirty years had passed. It was replaced when the <a class=\"Ref\" href=\"https://www.oxfordlearnersdictionaries.com/definition/english/the-freedom-of-information-act#the_freedom_of_information_act_topg_1\" title=\"Freedom of Information Act definition\"><span class=\"ndv\">Freedom of Information Act</span></a> was passed in 2005.</span></span>    \n</li></ol><div class=\"pron-link\">Check pronunciation:\n                        <a href=\"https://www.oxfordlearnersdictionaries.com/pronunciation/english/the-thirty-year-rule\">the thirty-year rule</a></div></div>\n","matches":[],"relatives":[],"nearBys":["the Thirty-nine Articles","thirty-second note noun","the thirty-year rule noun","this determiner, pronoun","this adverb"]},{"name":"Thirty days hath September","pos":"adjective","content":"<div class=\"entry\" hclass=\"entry\" sum=\"364\" sk=\"thirtydayshathseptember: :10\" htag=\"section\" id=\"thirty-days-hath-september\" hlength=\"26\" idm_id=\"000060966\"><div class=\"top-container\"><div class=\"top-g\" id=\"thirty_days_hath_september_topg_1\"><div class=\"webtop\"><h1 class=\"headword\" title=\"y\" id=\"thirty_days_hath_september_h_1\" htag=\"h1\" hclass=\"headword\">Thirty days hath September</h1> <span class=\"phonetics\"> <div class=\"phons_br\" geo=\"br\" htag=\"div\" hclass=\"phons_br\" wd=\"Thirty days hath September\"><div class=\"sound audio_play_button pron-uk icon-audio\" data-src-mp3=\"https://www.oxfordlearnersdictionaries.com/media/english/uk_pron/t/thi/thirt/thirty_days_hath_september_1_gb_1.mp3\" data-src-ogg=\"https://www.oxfordlearnersdictionaries.com/media/english/uk_pron_ogg/t/thi/thirt/thirty_days_hath_september_1_gb_1.ogg\" title=\"Thirty days hath September pronunciation\n                    English\" style=\"cursor: pointer\" valign=\"top\">&nbsp;</div><span class=\"phon\">/ˌθɜːti deɪz ˌhæθ sepˈtembə(r)/</span></div> <div class=\"phons_n_am\" geo=\"n_am\" htag=\"div\" wd=\"Thirty days hath September\" hclass=\"phons_n_am\"><div class=\"sound audio_play_button pron-us icon-audio\" data-src-mp3=\"https://www.oxfordlearnersdictionaries.com/media/english/us_pron/t/thi/thirt/thirty_days_hath_september_1_us_1.mp3\" data-src-ogg=\"https://www.oxfordlearnersdictionaries.com/media/english/us_pron_ogg/t/thi/thirt/thirty_days_hath_september_1_us_1.ogg\" title=\"Thirty days hath September pronunciation\n                    American\" style=\"cursor: pointer\" valign=\"top\">&nbsp;</div><span class=\"phon\">/ˌθɜːrti deɪz ˌhæθ sepˈtembər/</span></div></span></div><a class=\"responsive_display_inline_on_smartphone link-right\" href=\"#relatedentries\">\n                            jump to other results\n                        </a></div></div><ol class=\"sense_single\" htag=\"ol\"><li class=\"sense\" htag=\"li\" id=\"thirtydayshathseptember_sng_1\" hclass=\"sense\"><span class=\"sensetop\" hclass=\"sensetop\" htag=\"span\"><span class=\"def\" hclass=\"def\" htag=\"span\">the first line of a traditional <a class=\"Ref\" href=\"https://www.oxfordlearnersdictionaries.com/definition/english/rhyme_1\" title=\"rhyme definition\"><span class=\"ndv\">rhyme</span></a> which helps people to remember how many days there are in each month. The words are: <span class=\"blockquote\"><span class=\"p-g\"><span class=\"wrap_open\">“</span><span class=\"p\">Thirty days hath September,</span><span class=\"p\">April, June and November.</span><span class=\"p\">All the rest have thirty-one</span><span class=\"p\">Excepting February alone.</span><span class=\"wrap_close\">”</span></span></span></span></span>    \n</li></ol><div class=\"pron-link\">Check pronunciation:\n                        <a href=\"https://www.oxfordlearnersdictionaries.com/pronunciation/english/thirty-days-hath-september\">Thirty days hath September</a></div></div>\n","matches":[],"relatives":[],"nearBys":["thirtieth ordinal number","thirty","Thirty days hath September","the 38th parallel","35 mm noun"]},{"name":"the Thirty-nine Articles","pos":"adjective","content":"<div class=\"entry\" sk=\"thirtyninearticles: :30\" htag=\"section\" hlength=\"24\" id=\"the-thirty-nine-articles\" hclass=\"entry\" sum=\"455\" idm_id=\"000060969\"><div class=\"top-container\"><div class=\"top-g\" id=\"the_thirty_nine_articles_topg_1\"><div class=\"webtop\"><h1 class=\"headword\" htag=\"h1\" id=\"the_thirty_nine_articles_h_1\" hclass=\"headword\"><span class=\"st\" id=\"the_thirty_nine_articles_st_1\">the</span> Thirty-nine Articles</h1> <span class=\"phonetics\"> <div class=\"phons_br\" geo=\"br\" htag=\"div\" wd=\"the Thirty-nine Articles\" hclass=\"phons_br\"><div class=\"sound audio_play_button pron-uk icon-audio\" data-src-mp3=\"https://www.oxfordlearnersdictionaries.com/media/english/uk_pron/t/thi/thirt/thirty_nine_articles_1_gb_1.mp3\" data-src-ogg=\"https://www.oxfordlearnersdictionaries.com/media/english/uk_pron_ogg/t/thi/thirt/thirty_nine_articles_1_gb_1.ogg\" title=\"the Thirty-nine Articles pronunciation\n                    English\" style=\"cursor: pointer\" valign=\"top\">&nbsp;</div><span class=\"phon\">/ðə ˌθɜːti naɪn ˈɑːtɪklz/</span></div> <div class=\"phons_n_am\" geo=\"n_am\" htag=\"div\" wd=\"the Thirty-nine Articles\" hclass=\"phons_n_am\"><div class=\"sound audio_play_button pron-us icon-audio\" data-src-mp3=\"https://www.oxfordlearnersdictionaries.com/media/english/us_pron/t/thi/thirt/thirty_nine_articles_1_us_1.mp3\" data-src-ogg=\"https://www.oxfordlearnersdictionaries.com/media/english/us_pron_ogg/t/thi/thirt/thirty_nine_articles_1_us_1.ogg\" title=\"the Thirty-nine Articles pronunciation\n                    American\" style=\"cursor: pointer\" valign=\"top\">&nbsp;</div><span class=\"phon\">/ðə ˌθɜːrti naɪn ˈɑːrtɪklz/</span></div></span></div><a class=\"responsive_display_inline_on_smartphone link-right\" href=\"#relatedentries\">\n                            jump to other results\n                        </a></div></div><ol class=\"sense_single\" htag=\"ol\"><li class=\"sense\" id=\"thirtyninearticles_sng_1\" htag=\"li\" hclass=\"sense\"><span class=\"sensetop\" htag=\"span\" hclass=\"sensetop\"><span class=\"def\" hclass=\"def\" htag=\"span\">the set of religious principles that form the basic beliefs of the <a class=\"Ref\" href=\"https://www.oxfordlearnersdictionaries.com/definition/english/the-church-of-england\" title=\"Church of England definition\"><span class=\"ndv\">Church of England</span></a>. They were agreed upon in 1571 and were based on an earlier set produced by <a class=\"Ref\" href=\"https://www.oxfordlearnersdictionaries.com/definition/english/thomas-cranmer\" title=\"Thomas Cranmer definition\"><span class=\"ndv\">Thomas Cranmer</span></a> in 1563. Traditionally they are printed at the end of <a class=\"Ref\" href=\"https://www.oxfordlearnersdictionaries.com/definition/english/the-book-of-common-prayer#the_book_of_common_prayer_topg_1\" title=\"The Book of Common Prayer definition\"><span class=\"ndv\">The Book of Common Prayer</span></a> and anyone becoming a minister in the Church of England has to agree with them.</span></span>    \n</li></ol><div class=\"pron-link\">Check pronunciation:\n                        <a href=\"https://www.oxfordlearnersdictionaries.com/pronunciation/english/the-thirty-nine-articles\">the Thirty-nine Articles</a></div></div>\n","matches":[],"relatives":[],"nearBys":["the 38th parallel","35 mm noun","the Thirty-nine Articles","thirty-second note noun","the thirty-year rule noun"]},{"name":"demisemiquaver","pos":"noun","content":"<div class=\"entry\" htag=\"section\" id=\"demisemiquaver\" hlength=\"14\" sk=\"demisemiquaver: :0\" sum=\"210\" hclass=\"entry\" idm_id=\"000015610\"><div class=\"top-container\"><div class=\"top-g\" id=\"demisemiquaver_topg_1\"><div class=\"webtop\"><h1 class=\"headword\" id=\"demisemiquaver_h_1\" htag=\"h1\" hclass=\"headword\">demisemiquaver</h1> <span class=\"pos\" htag=\"span\" hclass=\"pos\">noun</span><span class=\"phonetics\"> <div class=\"phons_br\" wd=\"demisemiquaver\" hclass=\"phons_br\" htag=\"div\" geo=\"br\"><div class=\"sound audio_play_button pron-uk icon-audio\" data-src-mp3=\"https://www.oxfordlearnersdictionaries.com/media/english/uk_pron/d/dem/demis/demisemiquaver__gb_3.mp3\" data-src-ogg=\"https://www.oxfordlearnersdictionaries.com/media/english/uk_pron_ogg/d/dem/demis/demisemiquaver__gb_3.ogg\" title=\"demisemiquaver pronunciation\n                    English\" style=\"cursor: pointer\" valign=\"top\">&nbsp;</div><span class=\"phon\">/ˌdemiˈsemikweɪvə(r)/</span></div> <div class=\"phons_n_am\" htag=\"div\" geo=\"n_am\" hclass=\"phons_n_am\" wd=\"demisemiquaver\"><div class=\"sound audio_play_button pron-us icon-audio\" data-src-mp3=\"https://www.oxfordlearnersdictionaries.com/media/english/us_pron/d/dem/demis/demisemiquaver__us_1.mp3\" data-src-ogg=\"https://www.oxfordlearnersdictionaries.com/media/english/us_pron_ogg/d/dem/demis/demisemiquaver__us_1.ogg\" title=\"demisemiquaver pronunciation\n                    American\" style=\"cursor: pointer\" valign=\"top\">&nbsp;</div><span class=\"phon\">/ˌdemiˈsemikweɪvər/</span></div></span><span class=\"labels\" hclass=\"labels\" htag=\"span\">(British English)</span> <div class=\"variants\" id=\"demisemiquaver_vgs_1\" htag=\"div\" hclass=\"variants\" type=\"vf\">(<span class=\"v-g\" id=\"demisemiquaver_vg_1\"><span class=\"labels\" htag=\"span\" hclass=\"labels\">North American English</span> <span class=\"v\" id=\"demisemiquaver_v_1\">thirty-second note</span></span>)</div> <span class=\"labels\" htag=\"span\" hclass=\"labels\">(<span class=\"subj\" subj=\"music\" id=\"demisemiquaver_subj_1\">music</span>)</span></div><a class=\"responsive_display_inline_on_smartphone link-right\" href=\"#relatedentries\">\n                            jump to other results\n                        </a></div></div><ol class=\"sense_single\" htag=\"ol\"><li class=\"sense\" htag=\"li\" id=\"demisemiquaver_sng_1\" hclass=\"sense\"><span class=\"sensetop\" hclass=\"sensetop\" htag=\"span\"><span class=\"def\" hclass=\"def\" htag=\"span\">a note that lasts as long as half a <a class=\"Ref\" href=\"https://www.oxfordlearnersdictionaries.com/definition/english/semiquaver\" title=\"semiquaver definition\"><span class=\"ndv\">semiquaver</span></a></span></span>    \n</li></ol><div class=\"pron-link\">Check pronunciation:\n                        <a href=\"https://www.oxfordlearnersdictionaries.com/pronunciation/english/demisemiquaver\">demisemiquaver</a></div></div>\n","matches":["demisemiquaver"],"relatives":["demisemiquaver"],"nearBys":["demise noun","demi-sec adjective","demisemiquaver noun","demist verb","demister noun"]},{"name":"the thirty-year rule","pos":"noun","content":"<div class=\"entry\" htag=\"section\" id=\"the-thirty-year-rule\" hlength=\"20\" sk=\"thirtyyearrule: :20\" sum=\"348\" hclass=\"entry\" idm_id=\"000060971\"><div class=\"top-container\"><div class=\"top-g\" id=\"the_thirty_year_rule_topg_1\"><div class=\"webtop\"><h1 class=\"headword\" htag=\"h1\" id=\"the_thirty_year_rule_h_1\" hclass=\"headword\"><span class=\"st\" id=\"the_thirty_year_rule_st_1\">the</span> thirty-year rule</h1> <span class=\"pos\" htag=\"span\" hclass=\"pos\">noun</span><span class=\"phonetics\"> <div class=\"phons_br\" wd=\"the thirty-year rule\" hclass=\"phons_br\" geo=\"br\" htag=\"div\"><div class=\"sound audio_play_button pron-uk icon-audio\" data-src-mp3=\"https://www.oxfordlearnersdictionaries.com/media/english/uk_pron/t/thi/thirt/thirty_year_rule_1_gb_1.mp3\" data-src-ogg=\"https://www.oxfordlearnersdictionaries.com/media/english/uk_pron_ogg/t/thi/thirt/thirty_year_rule_1_gb_1.ogg\" title=\"the thirty-year rule pronunciation\n                    English\" style=\"cursor: pointer\" valign=\"top\">&nbsp;</div><span class=\"phon\">/ðə ˌθɜːti ˈjɪə ruːl/</span><span class=\"sep\">,</span> <div class=\"sound audio_play_button pron-uk icon-audio\" data-src-mp3=\"https://www.oxfordlearnersdictionaries.com/media/english/uk_pron/t/the/the_t/the_thirty_year_rule_1_gb_1.mp3\" data-src-ogg=\"https://www.oxfordlearnersdictionaries.com/media/english/uk_pron_ogg/t/the/the_t/the_thirty_year_rule_1_gb_1.ogg\" title=\"the thirty-year rule pronunciation\n                    English\" style=\"cursor: pointer\" valign=\"top\">&nbsp;</div><span class=\"phon\">/ðə ˌθɜːti ˈjɜː ruːl/</span></div> <div class=\"phons_n_am\" geo=\"n_am\" htag=\"div\" wd=\"the thirty-year rule\" hclass=\"phons_n_am\"><div class=\"sound audio_play_button pron-us icon-audio\" data-src-mp3=\"https://www.oxfordlearnersdictionaries.com/media/english/us_pron/t/thi/thirt/thirty_year_rule_1_us_1.mp3\" data-src-ogg=\"https://www.oxfordlearnersdictionaries.com/media/english/us_pron_ogg/t/thi/thirt/thirty_year_rule_1_us_1.ogg\" title=\"the thirty-year rule pronunciation\n                    American\" style=\"cursor: pointer\" valign=\"top\">&nbsp;</div><span class=\"phon\">/ðə ˌθɜːrti ˈjɪr ruːl/</span></div></span><span class=\"grammar\" htag=\"span\" hclass=\"grammar\">[singular]</span></div><a class=\"responsive_display_inline_on_smartphone link-right\" href=\"#relatedentries\">\n                            jump to other results\n                        </a></div></div><ol class=\"sense_single\" htag=\"ol\"><li class=\"sense\" htag=\"li\" id=\"thirtyyearrule_sng_1\" hclass=\"sense\"><span class=\"sensetop\" htag=\"span\" hclass=\"sensetop\"><span class=\"def\" htag=\"span\" hclass=\"def\">a British government rule which prevented certain official documents from being made public until a period of thirty years had passed. It was replaced when the <a class=\"Ref\" href=\"https://www.oxfordlearnersdictionaries.com/definition/english/the-freedom-of-information-act#the_freedom_of_information_act_topg_1\" title=\"Freedom of Information Act definition\"><span class=\"ndv\">Freedom of Information Act</span></a> was passed in 2005.</span></span>    \n</li></ol><div class=\"pron-link\">Check pronunciation:\n                        <a href=\"https://www.oxfordlearnersdictionaries.com/pronunciation/english/the-thirty-year-rule\">the thirty-year rule</a></div></div>\n","matches":[],"relatives":[],"nearBys":["the Thirty-nine Articles","thirty-second note noun","the thirty-year rule noun","this determiner, pronoun","this adverb"]},{"name":"thirty-second note","pos":"noun","content":"<div class=\"entry\" htag=\"section\" id=\"thirty-second-note\" hlength=\"18\" sk=\"thirtysecondnote: :15\" sum=\"291\" hclass=\"entry\" idm_id=\"000060970\"><div class=\"top-container\"><div class=\"top-g\" id=\"thirty_second_note_topg_1\"><div class=\"webtop\"><h1 class=\"headword\" htag=\"h1\" id=\"thirty_second_note_h_1\" hclass=\"headword\">thirty-second note</h1> <span class=\"pos\" htag=\"span\" hclass=\"pos\">noun</span><span class=\"phonetics\"> <div class=\"phons_br\" htag=\"div\" geo=\"br\" wd=\"thirty-second note\" hclass=\"phons_br\"><div class=\"sound audio_play_button pron-uk icon-audio\" data-src-mp3=\"https://www.oxfordlearnersdictionaries.com/media/english/uk_pron/t/thi/thirt/thirty_second_note_1_gb_1.mp3\" data-src-ogg=\"https://www.oxfordlearnersdictionaries.com/media/english/uk_pron_ogg/t/thi/thirt/thirty_second_note_1_gb_1.ogg\" title=\"thirty-second note pronunciation\n                    English\" style=\"cursor: pointer\" valign=\"top\">&nbsp;</div><span class=\"phon\">/ˌθɜːti ˈsekənd nəʊt/</span></div> <div class=\"phons_n_am\" htag=\"div\" geo=\"n_am\" wd=\"thirty-second note\" hclass=\"phons_n_am\"><div class=\"sound audio_play_button pron-us icon-audio\" data-src-mp3=\"https://www.oxfordlearnersdictionaries.com/media/english/us_pron/t/thi/thirt/thirty_second_note_1_us_1.mp3\" data-src-ogg=\"https://www.oxfordlearnersdictionaries.com/media/english/us_pron_ogg/t/thi/thirt/thirty_second_note_1_us_1.ogg\" title=\"thirty-second note pronunciation\n                    American\" style=\"cursor: pointer\" valign=\"top\">&nbsp;</div><span class=\"phon\">/ˌθɜːrti ˈsekənd nəʊt/</span></div></span><span class=\"labels\" htag=\"span\" hclass=\"labels\">(North American English)</span> <div class=\"variants\" id=\"thirty_second_note_vgs_1\" htag=\"div\" type=\"vf\" hclass=\"variants\">(<span class=\"v-g\" id=\"thirty_second_note_vg_1\"><span class=\"labels\" hclass=\"labels\" htag=\"span\">British English</span> <span class=\"v\" id=\"thirty_second_note_v_1\">demisemiquaver</span></span>)</div> <span class=\"labels\" hclass=\"labels\" htag=\"span\">(<span class=\"subj\" subj=\"music\" id=\"thirty_second_note_subj_1\">music</span>)</span></div><a class=\"responsive_display_inline_on_smartphone link-right\" href=\"#relatedentries\">\n                            jump to other results\n                        </a></div></div><ol class=\"sense_single\" htag=\"ol\"><li class=\"sense\" hclass=\"sense\" id=\"thirtysecondnote_sng_1\" htag=\"li\"><span class=\"sensetop\" hclass=\"sensetop\" htag=\"span\"><span class=\"def\" htag=\"span\" hclass=\"def\">a note that lasts as long as half a <a class=\"Ref\" href=\"https://www.oxfordlearnersdictionaries.com/definition/english/semiquaver\" title=\"semiquaver definition\"><span class=\"ndv\">semiquaver</span></a></span></span>    \n</li></ol><span class=\"dictlink-g\"><span class=\"dictlink\">See <a class=\"Ref\" href=\"https://www.oxfordlearnersdictionaries.com/definition/american_english/thirty-second-note\" title=\" definition in American English\n \"><span class=\"xh\">thirty-second note</span></a> in the Oxford Advanced American Dictionary</span></span><div class=\"pron-link\">Check pronunciation:\n                        <a href=\"https://www.oxfordlearnersdictionaries.com/pronunciation/english/thirty-second-note\">thirty-second note</a></div></div>\n","matches":["thirty-second note"],"relatives":["thirty-second note"],"nearBys":["35 mm noun","the Thirty-nine Articles","thirty-second note noun","the thirty-year rule noun","this determiner, pronoun"]}]]